libkubeselector-0.0.3.data/purelib/libkubeselector/__init__.py
libkubeselector-0.0.3.data/purelib/libkubeselector/build.sh
libkubeselector-0.0.3.data/purelib/libkubeselector/go.mod
libkubeselector-0.0.3.data/purelib/libkubeselector/go.sum
libkubeselector-0.0.3.data/purelib/libkubeselector/libselector.py
libkubeselector-0.0.3.data/purelib/libkubeselector/libselector_wrapper.go
libkubeselector-0.0.3.data/purelib/libkubeselector/libselector_wrapper.h
libkubeselector-0.0.3.data/purelib/libkubeselector/libselector_wrapper.so
libkubeselector-0.0.3.data/purelib/libkubeselector/test.sh
libkubeselector-0.0.3.dist-info/LICENSE
libkubeselector-0.0.3.dist-info/METADATA
libkubeselector-0.0.3.dist-info/WHEEL
libkubeselector-0.0.3.dist-info/top_level.txt
libkubeselector-0.0.3.dist-info/RECORD
