Metadata-Version: 2.1
Name: libkubeselector
Version: 0.0.3
Summary: libkubeselector
Home-page: UNKNOWN
Author: Kuznetsov Andrey A.
Author-email: andreykyz@gmail.com
License: Apache Software License
Keywords: kubernetes lib wrapper selector api python golang
Platform: UNKNOWN
Classifier: Programming Language :: Python :: 3.7
Classifier: Programming Language :: Other
Classifier: Environment :: Console
Classifier: License :: OSI Approved :: Apache Software License
